setup.py
flask_pgsql.egg-info/PKG-INFO
flask_pgsql.egg-info/SOURCES.txt
flask_pgsql.egg-info/dependency_links.txt
flask_pgsql.egg-info/requires.txt
flask_pgsql.egg-info/top_level.txt
flask_postgresql/__init__.py