Metadata-Version: 2.1
Name: flask-pgsql
Version: 0.0.2
Summary: A PostgreSQL library for Flask inspired by Flask-SQLAlchemy. This library provides an easy-to-use interface for interacting with PostgreSQL databases in Flask applications.
Home-page: https://github.com/thefcraft/flask_postgresql
Author: ThefCraft
Author-email: sisodiyalaksh@gmail.com
License: UNKNOWN
Platform: UNKNOWN
Classifier: Programming Language :: Python :: 3
Classifier: License :: OSI Approved :: MIT License
Classifier: Operating System :: OS Independent
